{"1994-01-01": {"Not in labor force": 119, "Employed": 36}, "1994-02-01": {"Not in labor force": 110, "Employed": 46, "Unemployed": 4}, "1994-03-01": {"Employed": 37, "Not in labor force": 112, "Unemployed": 3}, "1994-04-01": {"Unemployed": 9, "Not in labor force": 109, "Employed": 43}, "1994-05-01": {"Employed": 47, "Not in labor force": 120, "Unemployed": 9}, "1994-06-01": {"Not in labor force": 127, "Employed": 42, "Unemployed": 7}, "1994-07-01": {"Not in labor force": 118, "Employed": 33, "Unemployed": 8}, "1994-08-01": {"Not in labor force": 130, "Employed": 38, "Unemployed": 5}, "1994-09-01": {"Employed": 37, "Not in labor force": 110, "Unemployed": 4}, "1994-10-01": {"Not in labor force": 133, "Employed": 27, "Unemployed": 5}, "1994-11-01": {"Not in labor force": 148, "Employed": 33, "Unemployed": 7}, "1994-12-01": {"Not in labor force": 142, "Employed": 41, "Unemployed": 4}, "1995-01-01": {"Not in labor force": 142, "Employed": 36, "Unemployed": 6}, "1995-02-01": {"Not in labor force": 128, "Employed": 44, "Unemployed": 7}, "1995-03-01": {"Not in labor force": 118, "Employed": 37, "Unemployed": 7}, "1995-04-01": {"Not in labor force": 105, "Employed": 40, "Unemployed": 5}, "1995-05-01": {"Not in labor force": 123, "Employed": 42, "Unemployed": 3}, "1995-06-01": {"Not in labor force": 129, "Employed": 40, "Unemployed": 2}, "1995-07-01": {"Not in labor force": 129, "Employed": 33, "Unemployed": 4}, "1995-08-01": {"Not in labor force": 130, "Employed": 29, "Unemployed": 6}, "1995-09-01": {"Not in labor force": 107, "Employed": 33, "Unemployed": 6}, "1995-10-01": {"Not in labor force": 112, "Employed": 33, "Unemployed": 5}, "1995-11-01": {"Not in labor force": 115, "Employed": 33, "Unemployed": 5}, "1995-12-01": {"Not in labor force": 126, "Unemployed": 5, "Employed": 34}, "1996-06-01": {"Not in labor force": 112, "Employed": 35, "Unemployed": 3}, "1996-07-01": {"Not in labor force": 114, "Employed": 29, "Unemployed": 3}, "1996-08-01": {"Not in labor force": 115, "Employed": 34, "Unemployed": 4}, "1996-09-01": {"Not in labor force": 106, "Employed": 41, "Unemployed": 6}, "1996-10-01": {"Not in labor force": 101, "Unemployed": 3, "Employed": 38}, "1996-11-01": {"Not in labor force": 93, "Employed": 40, "Unemployed": 5}, "1996-12-01": {"Not in labor force": 115, "Employed": 33, "Unemployed": 2}, "1996-01-01": {"Not in labor force": 115, "Employed": 31, "Unemployed": 5}, "1997-01-01": {"Not in labor force": 106, "Employed": 26, "Unemployed": 8}, "1996-02-01": {"Not in labor force": 112, "Employed": 31, "Unemployed": 4}, "1997-02-01": {"Not in labor force": 114, "Employed": 23, "Unemployed": 5}, "1996-03-01": {"Not in labor force": 109, "Employed": 34, "Unemployed": 4}, "1997-03-01": {"Not in labor force": 112, "Unemployed": 6, "Employed": 29}, "1996-04-01": {"Not in labor force": 97, "Employed": 39, "Unemployed": 4}, "1997-04-01": {"Not in labor force": 107, "Employed": 46, "Unemployed": 5}, "1996-05-01": {"Employed": 30, "Not in labor force": 109, "Unemployed": 2}, "1997-05-01": {"Employed": 50, "Not in labor force": 101}, "1997-06-01": {"Employed": 45, "Not in labor force": 113, "Unemployed": 4}, "1997-07-01": {"Employed": 39, "Not in labor force": 114, "Unemployed": 1}, "1997-08-01": {"Not in labor force": 108, "Employed": 30, "Unemployed": 3}, "1997-09-01": {"Employed": 29, "Not in labor force": 110, "Unemployed": 5}, "1997-10-01": {"Not in labor force": 107, "Employed": 37, "Unemployed": 5}, "1997-11-01": {"Not in labor force": 111, "Employed": 37, "Unemployed": 2}, "1997-12-01": {"Not in labor force": 120, "Employed": 30, "Unemployed": 2}, "1998-01-01": {"Not in labor force": 115, "Employed": 34, "Unemployed": 5}, "1998-02-01": {"Not in labor force": 111, "Employed": 31, "Unemployed": 6}, "1998-03-01": {"Not in labor force": 111, "Employed": 38, "Unemployed": 5}, "1998-04-01": {"Not in labor force": 107, "Unemployed": 6, "Employed": 53}, "1998-05-01": {"Not in labor force": 102, "Employed": 54, "Unemployed": 5}, "1998-06-01": {"Not in labor force": 97, "Employed": 43, "Unemployed": 6}, "1998-07-01": {"Not in labor force": 97, "Employed": 37, "Unemployed": 2}, "1998-08-01": {"Employed": 37, "Not in labor force": 98, "Unemployed": 3}, "1998-09-01": {"Not in labor force": 104, "Employed": 28, "Unemployed": 3}, "1998-10-01": {"Not in labor force": 103, "Employed": 34, "Unemployed": 3}, "1998-11-01": {"Not in labor force": 115, "Employed": 38, "Unemployed": 2}, "1998-12-01": {"Not in labor force": 115, "Employed": 26, "Unemployed": 5}, "1999-01-01": {"Not in labor force": 114, "Employed": 30, "Unemployed": 6}, "1999-02-01": {"Not in labor force": 124, "Employed": 34, "Unemployed": 3}, "1999-03-01": {"Not in labor force": 111, "Unemployed": 3, "Employed": 30}, "1999-04-01": {"Not in labor force": 98, "Employed": 41, "Unemployed": 2}, "1999-05-01": {"Employed": 32, "Not in labor force": 97, "Unemployed": 3}, "1999-06-01": {"Not in labor force": 90, "Employed": 30, "Unemployed": 6}, "1999-07-01": {"Not in labor force": 100, "Employed": 28, "Unemployed": 5}, "1999-08-01": {"Not in labor force": 99, "Unemployed": 3, "Employed": 28}, "1999-09-01": {"Not in labor force": 103, "Employed": 32, "Unemployed": 2}, "1999-10-01": {"Not in labor force": 97, "Employed": 40, "Unemployed": 2}, "1999-11-01": {"Not in labor force": 102, "Employed": 35, "Unemployed": 3}, "1999-12-01": {"Not in labor force": 105, "Employed": 34, "Unemployed": 1}, "2000-01-01": {"Not in labor force": 104, "Employed": 25, "Unemployed": 2}, "2000-02-01": {"Not in labor force": 101, "Employed": 29, "Unemployed": 2}, "2000-03-01": {"Not in labor force": 107, "Employed": 25, "Unemployed": 1}, "2000-04-01": {"Employed": 29, "Not in labor force": 98}, "2000-05-01": {"Not in labor force": 93, "Employed": 30, "Unemployed": 1}, "2000-06-01": {"Not in labor force": 101, "Employed": 29, "Unemployed": 2}, "2000-07-01": {"Not in labor force": 93, "Employed": 28, "Unemployed": 4}, "2000-08-01": {"Not in labor force": 94, "Employed": 35, "Unemployed": 4}, "2000-09-01": {"Not in labor force": 97, "Employed": 30, "Unemployed": 3}, "2000-10-01": {"Not in labor force": 84, "Employed": 33, "Unemployed": 7}, "2000-11-01": {"Employed": 29, "Not in labor force": 94, "Unemployed": 7}, "2000-12-01": {"Not in labor force": 97, "Employed": 33, "Unemployed": 3}, "2001-01-01": {"Not in labor force": 99, "Employed": 27, "Unemployed": 4}, "2001-02-01": {"Not in labor force": 98, "Unemployed": 4, "Employed": 31}, "2001-03-01": {"Not in labor force": 95, "Employed": 32, "Unemployed": 2}, "2001-04-01": {"Not in labor force": 96, "Employed": 37, "Unemployed": 1}, "2001-05-01": {"Not in labor force": 97, "Employed": 36, "Unemployed": 3}, "2001-06-01": {"Not in labor force": 96, "Employed": 30, "Unemployed": 2}, "2001-07-01": {"Not in labor force": 98, "Employed": 32}, "2001-08-01": {"Not in labor force": 100, "Employed": 37, "Unemployed": 3}, "2001-09-01": {"Employed": 32, "Not in labor force": 111, "Unemployed": 5}, "2001-10-01": {"Not in labor force": 102, "Employed": 23, "Unemployed": 4}, "2001-11-01": {"Not in labor force": 110, "Employed": 22, "Unemployed": 4}, "2001-12-01": {"Not in labor force": 90, "Employed": 25, "Unemployed": 7}, "2002-01-01": {"Not in labor force": 89, "Employed": 27, "Unemployed": 6}, "2002-02-01": {"Not in labor force": 111, "Employed": 27, "Unemployed": 6}, "2002-03-01": {"Not in labor force": 107, "Employed": 34, "Unemployed": 7}, "2002-04-01": {"Not in labor force": 117, "Employed": 31, "Unemployed": 5}, "2002-05-01": {"Employed": 36, "Not in labor force": 115, "Unemployed": 4}, "2002-06-01": {"Employed": 33, "Not in labor force": 119, "Unemployed": 3}, "2002-07-01": {"Not in labor force": 113, "Employed": 31, "Unemployed": 3}, "2002-08-01": {"Not in labor force": 107, "Employed": 42, "Unemployed": 4}, "2002-09-01": {"Employed": 35, "Not in labor force": 119, "Unemployed": 4}, "2002-10-01": {"Not in labor force": 119, "Employed": 34, "Unemployed": 2}, "2002-11-01": {"Not in labor force": 116, "Employed": 25, "Unemployed": 9}, "2002-12-01": {"Not in labor force": 113, "Unemployed": 8, "Employed": 25}, "2003-01-01": {"Not in labor force": 105, "Employed": 29, "Unemployed": 7}, "2003-02-01": {"Not in labor force": 105, "Employed": 29, "Unemployed": 6}, "2003-03-01": {"Not in labor force": 106, "Unemployed": 7, "Employed": 28}, "2003-04-01": {"Not in labor force": 117, "Employed": 34, "Unemployed": 3}, "2003-05-01": {"Not in labor force": 110, "Employed": 33, "Unemployed": 5}, "2003-06-01": {"Not in labor force": 109, "Employed": 31, "Unemployed": 5}, "2003-07-01": {"Not in labor force": 110, "Employed": 28, "Unemployed": 5}, "2003-08-01": {"Not in labor force": 120, "Employed": 33, "Unemployed": 4}, "2003-09-01": {"Not in labor force": 114, "Unemployed": 7, "Employed": 28}, "2003-10-01": {"Not in labor force": 117, "Employed": 34, "Unemployed": 8}, "2003-11-01": {"Not in labor force": 100, "Employed": 29, "Unemployed": 7}, "2003-12-01": {"Not in labor force": 95, "Employed": 29, "Unemployed": 9}, "2004-01-01": {"Unemployed": 4, "Not in labor force": 102, "Employed": 25}, "2004-02-01": {"Employed": 28, "Not in labor force": 97, "Unemployed": 2}, "2004-03-01": {"Not in labor force": 93, "Employed": 32, "Unemployed": 4}, "2004-04-01": {"Not in labor force": 94, "Employed": 24, "Unemployed": 3}, "2004-05-01": {"Not in labor force": 97, "Employed": 29, "Unemployed": 3}, "2004-06-01": {"Not in labor force": 102, "Employed": 34, "Unemployed": 5}, "2004-07-01": {"Not in labor force": 105, "Employed": 31, "Unemployed": 4}, "2004-08-01": {"Not in labor force": 107, "Employed": 33, "Unemployed": 4}, "2004-09-01": {"Not in labor force": 94, "Employed": 26, "Unemployed": 4}, "2004-10-01": {"Not in labor force": 97, "Employed": 31, "Unemployed": 4}, "2004-11-01": {"Not in labor force": 88, "Employed": 25, "Unemployed": 4}, "2004-12-01": {"Not in labor force": 95, "Employed": 32, "Unemployed": 4}, "2005-01-01": {"Not in labor force": 97, "Employed": 46, "Unemployed": 5}, "2005-02-01": {"Not in labor force": 105, "Employed": 34, "Unemployed": 2}, "2005-03-01": {"Employed": 34, "Not in labor force": 110, "Unemployed": 5}, "2005-04-01": {"Not in labor force": 108, "Employed": 29, "Unemployed": 8}, "2005-05-01": {"Employed": 32, "Not in labor force": 117, "Unemployed": 4}, "2005-06-01": {"Not in labor force": 114, "Employed": 37, "Unemployed": 7}, "2005-07-01": {"Not in labor force": 94, "Employed": 40, "Unemployed": 5}, "2005-08-01": {"Not in labor force": 90, "Employed": 32, "Unemployed": 1}, "2005-09-01": {"Not in labor force": 76, "Employed": 29}, "2005-10-01": {"Not in labor force": 77, "Employed": 25, "Unemployed": 5}, "2005-11-01": {"Employed": 26, "Not in labor force": 75, "Unemployed": 2}, "2005-12-01": {"Not in labor force": 79, "Employed": 24, "Unemployed": 5}, "2006-01-01": {"Not in labor force": 81, "Employed": 30, "Unemployed": 4}, "2006-02-01": {"Not in labor force": 82, "Employed": 31, "Unemployed": 2}, "2006-03-01": {"Not in labor force": 97, "Employed": 27, "Unemployed": 4}, "2006-04-01": {"Not in labor force": 97, "Employed": 40, "Unemployed": 1}, "2006-05-01": {"Not in labor force": 85, "Unemployed": 5, "Employed": 30}, "2006-06-01": {"Not in labor force": 84, "Unemployed": 7, "Employed": 30}, "2006-07-01": {"Employed": 36, "Not in labor force": 76, "Unemployed": 2}, "2006-08-01": {"Not in labor force": 84, "Employed": 31, "Unemployed": 1}, "2006-09-01": {"Not in labor force": 79, "Employed": 29, "Unemployed": 1}, "2006-10-01": {"Not in labor force": 83, "Employed": 32, "Unemployed": 2}, "2006-11-01": {"Not in labor force": 79, "Employed": 28, "Unemployed": 4}, "2006-12-01": {"Not in labor force": 75, "Employed": 22, "Unemployed": 1}, "2007-01-01": {"Employed": 24, "Unemployed": 1, "Not in labor force": 91}, "2007-02-01": {"Not in labor force": 89, "Employed": 28, "Unemployed": 4}, "2007-03-01": {"Unemployed": 5, "Employed": 26, "Not in labor force": 97}, "2007-04-01": {"Employed": 31, "Not in labor force": 106, "Unemployed": 1}, "2007-05-01": {"Not in labor force": 96, "Employed": 23, "Unemployed": 1}, "2007-06-01": {"Not in labor force": 82, "Employed": 21, "Unemployed": 2}, "2007-07-01": {"Not in labor force": 75, "Employed": 26, "Unemployed": 2}, "2007-08-01": {"Not in labor force": 75, "Employed": 27, "Unemployed": 2}, "2007-09-01": {"Not in labor force": 76, "Employed": 27, "Unemployed": 5}, "2007-10-01": {"Employed": 25, "Not in labor force": 80, "Unemployed": 6}, "2007-11-01": {"Unemployed": 5, "Not in labor force": 71, "Employed": 23}, "2007-12-01": {"Not in labor force": 78, "Employed": 18, "Unemployed": 2}, "2008-01-01": {"Not in labor force": 85, "Employed": 20, "Unemployed": 3}, "2008-02-01": {"Not in labor force": 91, "Employed": 28}, "2008-03-01": {"Not in labor force": 101, "Employed": 31, "Unemployed": 2}, "2008-04-01": {"Not in labor force": 98, "Employed": 31, "Unemployed": 2}, "2008-05-01": {"Not in labor force": 93, "Employed": 23, "Unemployed": 4}, "2008-06-01": {"Not in labor force": 84, "Unemployed": 3, "Employed": 24}, "2008-07-01": {"Not in labor force": 73, "Employed": 15, "Unemployed": 5}, "2008-08-01": {"Unemployed": 3, "Not in labor force": 83, "Employed": 21}, "2008-09-01": {"Not in labor force": 78, "Employed": 18, "Unemployed": 7}, "2008-10-01": {"Not in labor force": 70, "Employed": 19, "Unemployed": 9}, "2008-11-01": {"Unemployed": 7, "Not in labor force": 73, "Employed": 19}, "2008-12-01": {"Not in labor force": 72, "Unemployed": 3, "Employed": 20}, "2009-01-01": {"Not in labor force": 84, "Employed": 13, "Unemployed": 8}, "2009-02-01": {"Not in labor force": 83, "Unemployed": 3, "Employed": 14}, "2009-03-01": {"Not in labor force": 91, "Employed": 14, "Unemployed": 6}, "2009-04-01": {"Not in labor force": 82, "Employed": 11, "Unemployed": 4}, "2009-05-01": {"Not in labor force": 77, "Employed": 15, "Unemployed": 4}, "2009-06-01": {"Not in labor force": 79, "Employed": 18, "Unemployed": 3}, "2009-07-01": {"Not in labor force": 81, "Employed": 17, "Unemployed": 2}, "2009-08-01": {"Not in labor force": 90, "Employed": 19, "Unemployed": 5}, "2009-09-01": {"Not in labor force": 87, "Employed": 19, "Unemployed": 4}, "2009-10-01": {"Not in labor force": 83, "Employed": 25, "Unemployed": 8}, "2009-11-01": {"Employed": 21, "Not in labor force": 73, "Unemployed": 9}, "2009-12-01": {"Not in labor force": 67, "Employed": 21, "Unemployed": 5}, "2010-01-01": {"Employed": 18, "Not in labor force": 80, "Unemployed": 7}, "2010-02-01": {"Not in labor force": 74, "Employed": 16, "Unemployed": 8}, "2010-03-01": {"Not in labor force": 81, "Employed": 22, "Unemployed": 5}, "2010-04-01": {"Unemployed": 7, "Not in labor force": 95, "Employed": 21}, "2010-05-01": {"Not in labor force": 75, "Employed": 18, "Unemployed": 5}, "2010-06-01": {"Not in labor force": 85, "Employed": 21, "Unemployed": 5}, "2010-07-01": {"Not in labor force": 79, "Employed": 21, "Unemployed": 8}, "2010-08-01": {"Not in labor force": 86, "Employed": 16, "Unemployed": 10}, "2010-09-01": {"Not in labor force": 90, "Employed": 18, "Unemployed": 11}, "2010-10-01": {"Not in labor force": 92, "Unemployed": 5, "Employed": 18}, "2010-11-01": {"Not in labor force": 82, "Employed": 16, "Unemployed": 5}, "2010-12-01": {"Not in labor force": 71, "Unemployed": 6, "Employed": 20}, "2011-01-01": {"Not in labor force": 81, "Employed": 23, "Unemployed": 6}, "2011-02-01": {"Not in labor force": 79, "Unemployed": 5, "Employed": 24}, "2011-03-01": {"Not in labor force": 75, "Employed": 21, "Unemployed": 6}, "2011-04-01": {"Not in labor force": 86, "Employed": 25, "Unemployed": 3}, "2011-05-01": {"Not in labor force": 72, "Employed": 21, "Unemployed": 9}, "2011-06-01": {"Not in labor force": 76, "Employed": 21, "Unemployed": 9}, "2011-07-01": {"Not in labor force": 81, "Employed": 25, "Unemployed": 5}, "2011-08-01": {"Not in labor force": 92, "Employed": 25, "Unemployed": 8}, "2011-09-01": {"Employed": 31, "Not in labor force": 94, "Unemployed": 4}, "2011-10-01": {"Not in labor force": 87, "Employed": 23, "Unemployed": 1}, "2011-11-01": {"Not in labor force": 90, "Employed": 17, "Unemployed": 3}, "2011-12-01": {"Not in labor force": 78, "Employed": 12, "Unemployed": 3}, "2012-01-01": {"Not in labor force": 80, "Employed": 13, "Unemployed": 3}, "2012-02-01": {"Not in labor force": 82, "Unemployed": 7, "Employed": 19}, "2012-03-01": {"Employed": 24, "Not in labor force": 68, "Unemployed": 7}, "2012-04-01": {"Employed": 18, "Not in labor force": 72, "Unemployed": 6}, "2012-05-01": {"Not in labor force": 58, "Employed": 20, "Unemployed": 10}, "2012-06-01": {"Not in labor force": 68, "Unemployed": 6, "Employed": 15}, "2012-07-01": {"Not in labor force": 80, "Employed": 14, "Unemployed": 5}, "2012-08-01": {"Not in labor force": 83, "Unemployed": 5, "Employed": 15}, "2012-09-01": {"Not in labor force": 96, "Employed": 14, "Unemployed": 3}, "2012-10-01": {"Not in labor force": 94, "Employed": 11, "Unemployed": 1}, "2012-11-01": {"Not in labor force": 86, "Employed": 12, "Unemployed": 3}, "2012-12-01": {"Not in labor force": 88, "Employed": 13, "Unemployed": 5}, "2013-01-01": {"Not in labor force": 88, "Employed": 14, "Unemployed": 8}, "2013-02-01": {"Not in labor force": 80, "Employed": 18, "Unemployed": 7}, "2013-03-01": {"Not in labor force": 78, "Employed": 21, "Unemployed": 6}, "2013-04-01": {"Employed": 17, "Not in labor force": 77, "Unemployed": 6}, "2013-05-01": {"Not in labor force": 72, "Employed": 16, "Unemployed": 1}, "2013-06-01": {"Not in labor force": 60, "Employed": 12, "Unemployed": 6}, "2013-07-01": {"Not in labor force": 69, "Employed": 13, "Unemployed": 5}, "2013-08-01": {"Not in labor force": 67, "Employed": 14, "Unemployed": 3}, "2013-09-01": {"Not in labor force": 69, "Employed": 17, "Unemployed": 4}, "2013-10-01": {"Not in labor force": 71, "Employed": 17, "Unemployed": 3}, "2013-11-01": {"Not in labor force": 76, "Employed": 18, "Unemployed": 2}, "2013-12-01": {"Not in labor force": 74, "Employed": 19, "Unemployed": 6}, "2014-01-01": {"Not in labor force": 75, "Unemployed": 6, "Employed": 23}, "2014-02-01": {"Not in labor force": 73, "Employed": 27, "Unemployed": 5}, "2014-03-01": {"Not in labor force": 67, "Employed": 26, "Unemployed": 8}, "2014-04-01": {"Employed": 23, "Not in labor force": 70, "Unemployed": 6}, "2014-05-01": {"Not in labor force": 72, "Unemployed": 2, "Employed": 12}, "2014-06-01": {"Not in labor force": 67, "Employed": 15, "Unemployed": 1}, "2014-07-01": {"Not in labor force": 66, "Employed": 11, "Unemployed": 2}, "2014-08-01": {"Not in labor force": 79, "Employed": 13, "Unemployed": 3}, "2014-09-01": {"Not in labor force": 77, "Unemployed": 6, "Employed": 14}, "2014-10-01": {"Not in labor force": 79, "Unemployed": 5, "Employed": 15}, "2014-11-01": {"Not in labor force": 86, "Employed": 16, "Unemployed": 7}, "2014-12-01": {"Not in labor force": 75, "Employed": 20, "Unemployed": 7}, "2015-01-01": {"Not in labor force": 86, "Employed": 20, "Unemployed": 5}, "2015-02-01": {"Not in labor force": 70, "Employed": 22, "Unemployed": 5}, "2015-03-01": {"Not in labor force": 77, "Employed": 27, "Unemployed": 2}, "2015-04-01": {"Not in labor force": 77, "Unemployed": 5, "Employed": 26}, "2015-05-01": {"Not in labor force": 75, "Employed": 21, "Unemployed": 5}, "2015-06-01": {"Not in labor force": 73, "Employed": 22, "Unemployed": 4}, "2015-07-01": {"Employed": 18, "Not in labor force": 85, "Unemployed": 2}, "2015-08-01": {"Not in labor force": 100, "Employed": 19, "Unemployed": 3}, "2015-09-01": {"Not in labor force": 94, "Employed": 21, "Unemployed": 2}, "2015-10-01": {"Not in labor force": 86, "Employed": 22, "Unemployed": 5}, "2015-11-01": {"Not in labor force": 79, "Employed": 16, "Unemployed": 6}, "2015-12-01": {"Not in labor force": 80, "Employed": 14, "Unemployed": 4}, "2016-01-01": {"Not in labor force": 78, "Employed": 19, "Unemployed": 4}, "2016-02-01": {"Not in labor force": 84, "Employed": 18, "Unemployed": 2}, "2016-03-01": {"Not in labor force": 81, "Employed": 22, "Unemployed": 1}, "2016-04-01": {"Not in labor force": 79, "Employed": 23, "Unemployed": 4}, "2016-05-01": {"Not in labor force": 77, "Employed": 18, "Unemployed": 2}, "2016-06-01": {"Not in labor force": 62, "Employed": 20, "Unemployed": 3}, "2016-07-01": {"Not in labor force": 62, "Employed": 18, "Unemployed": 3}, "2016-08-01": {"Not in labor force": 64, "Employed": 23, "Unemployed": 2}, "2016-09-01": {"Not in labor force": 72, "Employed": 26, "Unemployed": 3}, "2016-10-01": {"Not in labor force": 63, "Employed": 22, "Unemployed": 2}, "2016-11-01": {"Not in labor force": 73, "Employed": 18, "Unemployed": 2}, "2016-12-01": {"Not in labor force": 78, "Unemployed": 3, "Employed": 19}, "2017-01-01": {"Not in labor force": 76, "Unemployed": 1, "Employed": 25}, "2017-02-01": {"Not in labor force": 86, "Employed": 24, "Unemployed": 1}, "2017-03-01": {"Employed": 31, "Not in labor force": 87, "Unemployed": 2}, "2017-04-01": {"Not in labor force": 64, "Employed": 23, "Unemployed": 3}, "2017-05-01": {"Unemployed": 6, "Employed": 17, "Not in labor force": 61}, "2017-06-01": {"Not in labor force": 58, "Employed": 15, "Unemployed": 3}, "2017-07-01": {"Employed": 14, "Unemployed": 3, "Not in labor force": 56}, "2017-08-01": {"Not in labor force": 66, "Employed": 12, "Unemployed": 5}, "2017-09-01": {"Not in labor force": 67, "Employed": 17, "Unemployed": 2}, "2017-10-01": {"Employed": 20, "Not in labor force": 69, "Unemployed": 1}, "2017-11-01": {"Not in labor force": 79, "Employed": 18, "Unemployed": 2}, "2017-12-01": {"Not in labor force": 84, "Employed": 17, "Unemployed": 2}, "2018-01-01": {"Not in labor force": 90, "Employed": 16}, "2018-02-01": {"Not in labor force": 83, "Employed": 19}, "2018-03-01": {"Not in labor force": 74, "Employed": 15, "Unemployed": 1}, "2018-04-01": {"Employed": 15, "Not in labor force": 63, "Unemployed": 1}, "2018-05-01": {"Not in labor force": 61, "Employed": 10}, "2018-06-01": {"Not in labor force": 64, "Unemployed": 1, "Employed": 10}, "2018-07-01": {"Not in labor force": 50, "Employed": 12}, "2018-08-01": {"Not in labor force": 62, "Unemployed": 2, "Employed": 10}, "2018-09-01": {"Not in labor force": 53, "Employed": 16, "Unemployed": 1}, "2018-10-01": {"Not in labor force": 59, "Employed": 11}, "2018-11-01": {"Not in labor force": 71, "Unemployed": 1, "Employed": 9}, "2018-12-01": {"Not in labor force": 58, "Employed": 10}, "2019-01-01": {"Not in labor force": 63, "Employed": 12}, "2019-02-01": {"Not in labor force": 61, "Employed": 14}, "2019-03-01": {"Employed": 12, "Not in labor force": 66, "Unemployed": 1}, "2019-04-01": {"Employed": 11, "Not in labor force": 67, "Unemployed": 1}, "2019-05-01": {"Not in labor force": 62, "Employed": 12, "Unemployed": 3}, "2019-06-01": {"Not in labor force": 53, "Employed": 11, "Unemployed": 2}, "2019-07-01": {"Not in labor force": 43, "Employed": 14, "Unemployed": 1}, "2019-08-01": {"Not in labor force": 55, "Employed": 14}, "2019-09-01": {"Employed": 12, "Not in labor force": 50, "Unemployed": 3}, "2019-10-01": {"Not in labor force": 54, "Unemployed": 1, "Employed": 12}, "2019-11-01": {"Not in labor force": 57, "Employed": 16}, "2019-12-01": {"Not in labor force": 51, "Unemployed": 2, "Employed": 12}, "2020-01-01": {"Employed": 10, "Not in labor force": 66, "Unemployed": 2}, "2020-02-01": {"Not in labor force": 70, "Employed": 16, "Unemployed": 3}, "2020-03-01": {"Not in labor force": 63, "Employed": 12, "Unemployed": 4}, "2020-04-01": {"Not in labor force": 60, "Employed": 8, "Unemployed": 4}, "2020-05-01": {"Employed": 8, "Not in labor force": 52, "Unemployed": 4}, "2020-06-01": {"Not in labor force": 47, "Employed": 7}, "2020-07-01": {"Not in labor force": 43, "Employed": 9, "Unemployed": 1}, "2020-08-01": {"Employed": 9, "Not in labor force": 45, "Unemployed": 4}, "2020-09-01": {"Employed": 15, "Not in labor force": 50, "Unemployed": 2}, "2020-10-01": {"Employed": 23, "Not in labor force": 56, "Unemployed": 2}, "2020-11-01": {"Not in labor force": 61, "Employed": 20, "Unemployed": 2}, "2020-12-01": {"Employed": 17, "Not in labor force": 52, "Unemployed": 2}, "2021-01-01": {"Not in labor force": 60, "Employed": 10, "Unemployed": 3}, "2021-02-01": {"Not in labor force": 61, "Employed": 10, "Unemployed": 3}, "2021-03-01": {"Not in labor force": 67, "Unemployed": 2, "Employed": 6}, "2021-04-01": {"Not in labor force": 62, "Employed": 9, "Unemployed": 3}, "2021-05-01": {"Employed": 8, "Not in labor force": 70, "Unemployed": 1}, "2021-06-01": {"Not in labor force": 68, "Employed": 10}, "2021-07-01": {"Not in labor force": 58, "Employed": 10, "Unemployed": 4}, "2021-08-01": {"Not in labor force": 64, "Employed": 16, "Unemployed": 1}, "2021-09-01": {"Not in labor force": 67, "Employed": 18, "Unemployed": 1}, "2021-10-01": {"Not in labor force": 61, "Employed": 14, "Unemployed": 3}, "2021-11-01": {"Not in labor force": 56, "Employed": 17, "Unemployed": 3}, "2021-12-01": {"Not in labor force": 57, "Employed": 10, "Unemployed": 3}, "2022-01-01": {"Not in labor force": 62, "Employed": 5, "Unemployed": 7}, "2022-02-01": {"Not in labor force": 61, "Employed": 8, "Unemployed": 1}, "2022-03-01": {"Not in labor force": 60, "Employed": 6}, "2022-04-01": {"Not in labor force": 59, "Employed": 8, "Unemployed": 1}, "2022-05-01": {"Not in labor force": 60, "Employed": 9, "Unemployed": 2}}