{"2008-12-01": {"Not in labor force": 1}, "2009-01-01": {"Not in labor force": 1}, "2009-02-01": {"Not in labor force": 1}, "2009-06-01": {"Not in labor force": 1}, "2009-07-01": {"Not in labor force": 1}, "2013-04-01": {"Employed": 1}, "2016-09-01": {"Not in labor force": 1}, "2016-10-01": {"Not in labor force": 1}, "2016-11-01": {"Not in labor force": 1}, "2016-12-01": {"Not in labor force": 1}, "2018-08-01": {"Not in labor force": 1}, "2018-09-01": {"Not in labor force": 1}, "2018-10-01": {"Not in labor force": 1}, "2018-11-01": {"Not in labor force": 1}, "2019-01-01": {"Not in labor force": 1}, "2019-02-01": {"Unemployed": 1}, "2019-03-01": {"Not in labor force": 1}, "2019-04-01": {"Not in labor force": 1}}